ticktok/__init__.py
ticktok/client.py
ticktok-0.1.0.dist-info/LICENSE
ticktok-0.1.0.dist-info/WHEEL
ticktok-0.1.0.dist-info/METADATA
ticktok-0.1.0.dist-info/RECORD
