Metadata-Version: 2.1
Name: ticktok
Version: 0.1.0
Summary: Official Python client for Ticktok.io
Author: elis
Requires-Python: >=3.6,<4.0
Classifier: Programming Language :: Python :: 3
Classifier: Programming Language :: Python :: 3.6
Classifier: Programming Language :: Python :: 3.7
Classifier: Programming Language :: Python :: 3.8
Classifier: Programming Language :: Python :: 3.9
